Metadata-Version: 2.1
Name: Mensajes-AlejandroDamas
Version: 6.0
Summary: Un paquete para saludar y despedir
Home-page: https://www.damas.py
Author: Alejandro Damas Pablos
Author-email: hola@damas.py
Classifier: Environment :: Console
Classifier: Intended Audience :: Developers
Classifier: License :: OSI Approved :: MIT License
Classifier: Operating System :: OS Independent
Classifier: Programming Language :: Python
Classifier: Programming Language :: Python :: 3.11
Classifier: Programming Language :: Python :: 3.12
Classifier: Topic :: Utilities
License-File: LICENSE
Requires-Dist: numpy (>=1.24.2)
